pawnlib/__init__.py
pawnlib/__main__.py
pawnlib/__version__.py
pawnlib/asyncio/__init__.py
pawnlib/asyncio/run.py
pawnlib/builder/__init__.py
pawnlib/builder/generator.py
pawnlib/builder/templates/__init__.py
pawnlib/cli/__init__.py
pawnlib/cli/aws.py
pawnlib/cli/http.py
pawnlib/cli/icon.py
pawnlib/cli/init.py
pawnlib/cli/main_cli.py
pawnlib/cli/proxy.py
pawnlib/config/__fix_import.py
pawnlib/config/__init__.py
pawnlib/config/configure.py
pawnlib/config/console.py
pawnlib/config/globalconfig.py
pawnlib/input/__init__.py
pawnlib/input/prompt.py
pawnlib/output/__init__.py
pawnlib/output/color_print.py
pawnlib/output/file.py
pawnlib/resource/__init__.py
pawnlib/resource/net.py
pawnlib/resource/server.py
pawnlib/typing/__init__.py
pawnlib/typing/check.py
pawnlib/typing/constants.py
pawnlib/typing/converter.py
pawnlib/typing/date_utils.py
pawnlib/typing/defines.py
pawnlib/typing/generator.py
pawnlib/utils/__init__.py
pawnlib/utils/http.py
pawnlib/utils/icx_signer.py
pawnlib/utils/log.py
pawnlib/utils/notify.py
pawnlib/utils/operate_handler.py
toolchains/__init__.py
toolchains/__main__.py
toolchains/__version__.py
toolchains/cli/__init__.py
toolchains/cli/_icon.py
toolchains/cli/aws.py
toolchains/cli/docker.py
toolchains/cli/http.py
toolchains/cli/main_cli.py
toolchains/cli/rpc.py
toolchains/cli/wallet.py
toolchains/cli/wallet__.py
toolchains/cli/websocket.py
toolchains/cli/templates/__init__.py
toolchains/cli/templates/docker_echo.tmpl
toolchains/cli/templates/docker_planet.tmpl
toolchains/db/__init__.py
toolchains/db/influxdb.py
toolchains/db/promethus.py
toolchains/docker/__init__.py
toolchains/docker/async_docker.py
toolchains/models/__init__.py
toolchains/models/http_models.py
toolchains/resource/DB_modeling.py
toolchains/resource/InfluxDB_Manager.py
toolchains/resource/__init__.py
toolchains/resource/alert_noti.py
toolchains/resource/test_noti.py
toolchains/resource/url_checker.py
toolchains/utils/__init__.py
toolchains/utils/http.py
toolchains/utils/icx_signer.py
toolchains-0.0.14.dist-info/METADATA
toolchains-0.0.14.dist-info/WHEEL
toolchains-0.0.14.dist-info/entry_points.txt
toolchains-0.0.14.dist-info/top_level.txt
toolchains-0.0.14.dist-info/zip-safe
toolchains-0.0.14.dist-info/RECORD
